fluxgate_ctl/__init__.py
fluxgate_ctl/__main__.py
fluxgate_ctl/discovery.py
fluxgate_ctl-1.0.14.dist-info/LICENSE
fluxgate_ctl-1.0.14.dist-info/METADATA
fluxgate_ctl-1.0.14.dist-info/WHEEL
fluxgate_ctl-1.0.14.dist-info/entry_points.txt
fluxgate_ctl-1.0.14.dist-info/top_level.txt
fluxgate_ctl-1.0.14.dist-info/RECORD
