Metadata-Version: 2.1
Name: fluxgate-ctl
Version: 1.0.14
Summary: fluxgate-ctl package for TUCAN
Author-email: Bryerton Shaw <bryerton@triumf.ca>
License: MIT License
License-File: LICENSE
Requires-Dist: zmq
Requires-Dist: matplotlib
Provides-Extra: dev
Requires-Dist: tox ; extra == 'dev'
